{"version":0.6,"generator":"Overpass API 0.7.61.5 4133829e","osm3s":{"timestamp_osm_base":"2023-08-16T10:56:13Z","copyright":"The data included in this document is from www.openstreetmap.org. The data is made available under ODbL."},"elements":[{"type":"node","id":293650408,"lat":37.948029,"lon":23.6643216,"tags":{"maxspeed":"40","traffic_sign":"maxspeed"}},{"type":"node","id":293650709,"lat":37.948237,"lon":23.664248,"tags":{"crossing":"marked","crossing:markings":"yes","crossing_ref":"zebra","highway":"crossing","note":"No traffic signals noted on survey, March 11 2014","source":"survey"}},{"type":"node","id":805848294,"lat":37.9482166,"lon":23.664125,"tags":{"crossing":"marked","crossing:markings":"yes","crossing_ref":"zebra","highway":"crossing","note":"No traffic signals noted on survey, March 11 2014","source":"survey"}},{"type":"node","id":805848467,"lat":37.9478679,"lon":23.6632089,"tags":{"crossing":"uncontrolled","crossing_ref":"zebra","highway":"crossing","source":"bing"}},{"type":"node","id":2753807221,"lat":37.9481733,"lon":23.6640384,"tags":{"crossing":"uncontrolled","crossing_ref":"zebra","highway":"crossing","note":"No traffic signals noted on survey, March 11 2014","source":"survey"}},{"type":"node","id":2753807227,"lat":37.9482388,"lon":23.6640267,"tags":{"crossing":"uncontrolled","crossing_ref":"zebra","highway":"crossing","note":"No traffic signals noted on survey, March 11 2014","source":"survey"}},{"type":"node","id":2753807229,"lat":37.9482576,"lon":23.6640764,"tags":{"highway":"stop"}},{"type":"node","id":2754418898,"lat":37.948745,"lon":23.664096,"tags":{"maxspeed":"40","traffic_sign":"maxspeed"}},{"type":"node","id":3972652334,"lat":37.9483969,"lon":23.6642001,"tags":{"note":"\u03a3\u03ae\u03bc\u03b1\u03c4\u03b1 \u03c4\u03b7\u03c2 \u03c4\u03c1\u03bf\u03c7\u03b1\u03af\u03b1\u03c2 \u03b1\u03c0\u03b1\u03b3\u03bf\u03c1\u03b5\u03cd\u03bf\u03c5\u03bd \u03c3\u03b1\u03c6\u03ce\u03c2 \u03c4\u03bf \u03c0\u03ad\u03c1\u03b1\u03c3\u03bc\u03b1 \u03b1\u03c0\u03cc \u03c4\u03bf \u00ab\u03b1\u03c0\u03ad\u03bd\u03b1\u03bd\u03c4\u03b9\u00bb \u03c1\u03b5\u03cd\u03bc\u03b1 \u03ae \u03b1\u03c0\u03cc \u03c4\u03b7 \u03a3\u03bf\u03c6\u03b9\u03b1\u03bd\u03bf\u03c0\u03bf\u03cd\u03bb\u03bf\u03c5 \u03c3\u03b5 \u03b1\u03c5\u03c4\u03cc \u03c4\u03bf \u00ab\u03c1\u03b5\u03cd\u03bc\u03b1\u00bb \u03c4\u03b7\u03c2 \u039a\u03b1\u03c1\u03b1\u03bf\u03bb\u03ae \u03ba\u03b1\u03b9 \u0394\u03b7\u03bc\u03b7\u03c4\u03c1\u03af\u03bf\u03c5."}}]}