{"version":0.6,"generator":"Overpass API 0.7.62.5 1bd436f1","osm3s":{"timestamp_osm_base":"2025-03-12T13:14:00Z","copyright":"The data included in this document is from www.openstreetmap.org. The data is made available under ODbL."},"elements":[{"type":"node","id":334557781,"lat":52.2224766,"lon":21.0164989,"tags":{"bus":"yes","name":"Plac Konstytucji 02","network":"ZTM Warszawa","operator":"Zarz\u0105d Transportu Miejskiego w Warszawie","public_transport":"stop_position","ref":"701102"}},{"type":"node","id":334558347,"lat":52.2223712,"lon":21.0158727,"tags":{"bus":"yes","name":"Plac Konstytucji 01","network":"ZTM Warszawa","operator":"Zarz\u0105d Transportu Miejskiego w Warszawie","public_transport":"stop_position","ref":"701101"}},{"type":"node","id":344563244,"lat":52.2225013,"lon":21.0155867,"tags":{"amenity":"grit_bin","check_date":"2021-05-13","seasonal":"winter"}},{"type":"node","id":344563245,"lat":52.2224151,"lon":21.0156336,"tags":{"amenity":"grit_bin","check_date":"2021-05-13","seasonal":"winter"}},{"type":"node","id":344563246,"lat":52.2223136,"lon":21.0156751,"tags":{"amenity":"grit_bin","check_date":"2021-05-13","seasonal":"winter"}},{"type":"node","id":692622971,"lat":52.2222512,"lon":21.0156826,"tags":{"name":"\u015ar\u00f3dmie\u015bcie Po\u0142udniowe","place":"quarter","wikidata":"Q9395946","wikipedia":"pl:\u015ar\u00f3dmie\u015bcie Po\u0142udniowe"}},{"type":"node","id":2334293064,"lat":52.2225757,"lon":21.0154979,"tags":{"leaf_type":"broadleaved","natural":"tree"}},{"type":"node","id":2334293065,"lat":52.2224085,"lon":21.0155044,"tags":{"leaf_type":"broadleaved","natural":"tree"}},{"type":"node","id":2334293068,"lat":52.2223145,"lon":21.0155605,"tags":{"leaf_type":"broadleaved","natural":"tree"}},{"type":"node","id":2334293074,"lat":52.2221674,"lon":21.0156464,"tags":{"leaf_type":"broadleaved","natural":"tree"}},{"type":"node","id":2334293075,"lat":52.2224568,"lon":21.0154753,"tags":{"leaf_type":"broadleaved","natural":"tree"}},{"type":"node","id":2334293079,"lat":52.2224265,"lon":21.0155869,"tags":{"leaf_type":"broadleaved","natural":"tree"}},{"type":"node","id":3406838436,"lat":52.2219629,"lon":21.0154538,"tags":{"addr:city":"Warszawa","addr:floor":"G","addr:housenumber":"5","addr:street":"Plac Konstytucji","check_date":"2024-04-08","level":"0","name":"Paris Optique","opening_hours":"Mo-Fr 10:30-19:30; Sa 10:00-16:00","shop":"optician","website":"https:\/\/www.parisoptique.pl\/","wheelchair":"yes"}},{"type":"node","id":3516310958,"lat":52.2221046,"lon":21.0154905,"tags":{"access":"yes","amenity":"bicycle_parking","bicycle_parking":"stands","capacity":"10","check_date:capacity":"2023-10-07","covered":"no","fee":"no"}},{"type":"node","id":3856725883,"lat":52.2220741,"lon":21.0155244,"tags":{"couplings":"2","emergency":"fire_hydrant","fire_hydrant:diameter":"150","fire_hydrant:position":"sidewalk","fire_hydrant:type":"pillar"}},{"type":"node","id":5236032587,"lat":52.2222689,"lon":21.0157121,"tags":{"bench":"yes","bin":"yes","bus":"yes","highway":"bus_stop","lit":"yes","name":"Plac Konstytucji 01","network":"ZTM Warszawa","network:wikidata":"Q8066998","network:wikipedia":"pl:Zarz\u0105d Transportu Miejskiego w Warszawie","operator":"Zarz\u0105d Transportu Miejskiego w Warszawie","public_transport":"platform","ref":"701101","shelter":"yes","tactile_paving":"yes","url":"https:\/\/www.wtp.waw.pl\/rozklady-jazdy\/?wtp_md=8&wtp_st=7011&wtp_pt=01"}},{"type":"node","id":8929471461,"lat":52.2221588,"lon":21.0157445,"tags":{"access":"yes","amenity":"bicycle_parking","bicycle_parking":"stands","capacity":"10","covered":"no","fee":"no"}},{"type":"node","id":9501290699,"lat":52.2223338,"lon":21.0162905,"tags":{"amenity":"vending_machine","operator":"ZDM Warszawa","ref":"G050122","vending":"parking_tickets"}},{"type":"node","id":9501290701,"lat":52.2226055,"lon":21.0161343,"tags":{"amenity":"vending_machine","operator":"ZDM Warszawa","ref":"G050123","vending":"parking_tickets"}},{"type":"node","id":9501290705,"lat":52.2219482,"lon":21.0160567,"tags":{"amenity":"vending_machine","operator":"ZDM Warszawa","ref":"G050120","vending":"parking_tickets"}},{"type":"node","id":9964335505,"lat":52.2222188,"lon":21.0157305,"tags":{"addr:floor":"G","amenity":"vending_machine","check_date":"2024-04-08","covered":"no","currency:PLN":"yes","indoor":"no","level":"0","network":"ZTM Warszawa","network:wikidata":"Q8066998","network:wikipedia":"pl:Zarz\u0105d Transportu Miejskiego w Warszawie","opening_hours":"24\/7","operator":"Mennica Polska","operator:wikidata":"Q4371256","operator:wikipedia":"pl:Mennica Polska","payment:coins":"yes","payment:contactless":"yes","payment:maestro":"yes","payment:mastercard":"yes","payment:notes":"yes","payment:v_pay":"yes","payment:visa":"yes","payment:visa_electron":"yes","ref":"1090","vending":"public_transport_tickets"}},{"type":"node","id":9964335506,"lat":52.2224095,"lon":21.0156024,"tags":{"addr:floor":"G","amenity":"vending_machine","check_date":"2024-04-08","covered":"no","currency:PLN":"yes","indoor":"no","level":"0","manufacturer":"Scheidt&Bachmann","network":"ZTM Warszawa","network:wikidata":"Q8066998","network:wikipedia":"pl:Zarz\u0105d Transportu Miejskiego w Warszawie","operator":"Mennica Polska","operator:wikidata":"Q4371256","operator:wikipedia":"pl:Mennica Polska","payment:coins":"yes","payment:contactless":"yes","payment:maestro":"yes","payment:mastercard":"yes","payment:notes":"yes","payment:v_pay":"yes","payment:visa":"yes","payment:visa_electron":"yes","ref":"495","vending":"public_transport_tickets"}},{"type":"node","id":10931366585,"lat":52.2224734,"lon":21.0156157,"tags":{"highway":"street_lamp"}},{"type":"node","id":10931366586,"lat":52.2222445,"lon":21.0157538,"tags":{"highway":"street_lamp"}},{"type":"node","id":11248974328,"lat":52.2225625,"lon":21.0155213,"tags":{"amenity":"waste_basket","material":"concrete"}},{"type":"node","id":11248974329,"lat":52.2223987,"lon":21.015607,"tags":{"amenity":"waste_basket","material":"concrete"}},{"type":"node","id":11248974330,"lat":52.2223067,"lon":21.0156889,"tags":{"amenity":"waste_basket","material":"concrete"}},{"type":"node","id":11248974331,"lat":52.2221908,"lon":21.0157268,"tags":{"leaf_type":"broadleaved","natural":"tree"}},{"type":"node","id":11248974332,"lat":52.2222642,"lon":21.0155891,"tags":{"was:leaf_type":"broadleaved","was:natural":"tree"}},{"type":"node","id":11248974333,"lat":52.2223622,"lon":21.0156265,"tags":{"amenity":"bench","backrest":"no","material":"wood"}},{"type":"node","id":11248974334,"lat":52.2223861,"lon":21.0156119,"tags":{"amenity":"bench","backrest":"no","material":"wood"}},{"type":"node","id":11248974335,"lat":52.2224479,"lon":21.015575,"tags":{"amenity":"bench","backrest":"no","material":"wood"}},{"type":"node","id":11248974336,"lat":52.2224665,"lon":21.0155642,"tags":{"amenity":"bench","backrest":"no","material":"wood"}},{"type":"node","id":11819907438,"lat":52.2223634,"lon":21.0164435,"tags":{"noexit":"yes"}}]}