{"version":0.6,"generator":"Overpass API 0.7.62.5 1bd436f1","osm3s":{"timestamp_osm_base":"2025-03-12T11:57:36Z","copyright":"The data included in this document is from www.openstreetmap.org. The data is made available under ODbL."},"elements":[{"type":"way","id":4041168,"nodes":[90067490,4027013174,312629229,308572872,90235391,6441628608,696848144,955932442,355920716,955935291,10762333877,21392399],"tags":{"bicycle":"yes","highway":"pedestrian","lit":"yes","motor_vehicle":"permissive","name":"High Street","oneway":"yes","postal_code":"B4","surface":"paving_stones","wikidata":"Q30068797"}},{"type":"way","id":10364525,"nodes":[268603476,1455180571,268601643,1744420739,908592240,1744420734,1744420726,908592241,159540357,178916275,7117546478,21392706],"tags":{"electrified":"no","gauge":"1435","layer":"-2","maxspeed":"20 mph","name":"Snow Hill Tunnel","passenger_lines":"2","railway":"rail","ref":"DCL","source":"OS-OpenData_StreetView","tunnel":"yes","tunnel:name":"Snow Hill Tunnel","usage":"main"}},{"type":"way","id":10595460,"nodes":[90052951,9135599700,5505854514,310651596,1153441440,90067490],"tags":{"bicycle":"yes","bus":"yes","foot":"yes","gritting":"priority_3","highway":"unclassified","lane_markings":"yes","lanes":"2","lit":"yes","maintenance":"gritting","maxspeed":"20 mph","motor_vehicle":"destination","name":"Carrs Lane","note":"restrictions as per TRO 3787308 https:\/\/www.thegazette.co.uk\/notice\/3787308","oneway":"yes","psv":"yes","shoulder":"no","source":"survey","source:maxspeed":"survey","surface":"asphalt"}},{"type":"way","id":28511015,"nodes":[313191022,313191023,313191024,313191025,863896111,313191017,308572882,313191022],"tags":{"addr:city":"Birmingham","addr:housenumber":"42","addr:postcode":"B4 7SS","addr:street":"High Street","architect":"James M Munro & Son","building":"retail","building:levels":"4","height":"13","old_name":"Marks & Spencer","shop":"vacant","start_date":"1956","toilets":"yes","wheelchair":"yes"}},{"type":"way","id":97238830,"nodes":[1126389002,1975383212,6249629009,1975383194,6034972697,1975375864,1975375865,863896101,863896139,313191021,1126389003,313191020,313191019,6410985130,6410985129,6464915489,6410985131,6464915490,6410985132,313191017,308572882,6441628607,313191015,313191014,6410985128,1126389002],"tags":{"addr:city":"Birmingham","addr:country":"GB","addr:housenumber":"38","addr:postcode":"B4 7SL","addr:street":"High Street","alt_name":"Primark Bullring;Primark Birmingham High Street","architect":"Chapman Taylor Partners","brand":"Primark","brand:wikidata":"Q137023","brand:wikipedia":"en:Primark","building":"retail","building:levels":"5","fhrs:id":"1157098","name":"Primark","opening_hours":"Mo-Sa 08:00-21:00; Su 11:00-17:00","shop":"clothes","source":"eyeball survey & estimate","start_date":"1986","website":"https:\/\/www.primark.com\/en-gb\/stores\/birmingham\/38-high-street"}},{"type":"way","id":132239456,"nodes":[1455177634,7117546477,1455180572,7117546480,1455180570,1827309440,1455180568,7117546479,1827309442,1827309427,1455180573,1455180569],"tags":{"electrified":"no","gauge":"1435","layer":"-2","maxspeed":"20 mph","name":"Snow Hill Tunnel","passenger_lines":"2","railway":"rail","ref":"DCL","source":"OS-OpenData_StreetView","tunnel":"yes","tunnel:name":"Snow Hill Tunnel","usage":"main"}},{"type":"way","id":144508162,"nodes":[1580643691,1580645688,1580645687,1683193631,1580645684,1580643689,1580643691],"tags":{"leisure":"park","source":"visual survey;bing"}},{"type":"way","id":324113242,"nodes":[273036406,90052953,2520425393,90052954,863896138,90052951],"tags":{"access":"yes","highway":"service","level":"1","lit":"yes","maxspeed":"20 mph","source":"cities_revealed_aerial_imagery","source:maxspeed":"TRO","surface":"asphalt"}},{"type":"way","id":400071575,"nodes":[863896136,956080706,956080710,696842445,10762333871,1261722749,1261722728,1261722715,4027013163,4027013184,4027013146,4027013168,4027013149,4027013156,4027013159,4027013174,4027013150,313191023,313191022,6441628609,6441628606,313191014,6410985128,1126389002,864881342,10762333877,863896136],"tags":{"area":"yes","bicycle":"designated","highway":"pedestrian","lit":"yes","surface":"paving_stones"}},{"type":"way","id":573201909,"nodes":[1153441440,5505854516,2523807528,5505854515],"tags":{"footway":"sidewalk","highway":"footway","lit":"yes","source":"bing","surface":"paving_stones"}},{"type":"way","id":687239426,"nodes":[313191014,6441628606,6441628607,313191015,313191014],"tags":{"building":"retail"}},{"type":"way","id":687239427,"nodes":[6441628608,6441628609,6441628610],"tags":{"check_date":"2024-04-14","highway":"service","name":"Castle Street","service":"alley","surface":"paving_stones","width":"3"}},{"type":"node","id":21392399,"lat":52.4785354,"lon":-1.8950831},{"type":"node","id":90067490,"lat":52.4797795,"lon":-1.8945229},{"type":"node","id":90235391,"lat":52.4795345,"lon":-1.8946576},{"type":"node","id":159540357,"lat":52.4799352,"lon":-1.8943678},{"type":"node","id":268601643,"lat":52.4823736,"lon":-1.8978072},{"type":"node","id":268603476,"lat":52.4828867,"lon":-1.8984597},{"type":"node","id":308572872,"lat":52.4796071,"lon":-1.8946245},{"type":"node","id":308572882,"lat":52.4793227,"lon":-1.8942632},{"type":"node","id":312629229,"lat":52.4796572,"lon":-1.8945968},{"type":"node","id":313191014,"lat":52.4791749,"lon":-1.894652},{"type":"node","id":313191015,"lat":52.479133,"lon":-1.8943394},{"type":"node","id":313191021,"lat":52.4784141,"lon":-1.8944734},{"type":"node","id":313191022,"lat":52.4793688,"lon":-1.8945776},{"type":"node","id":313191023,"lat":52.4796876,"lon":-1.8944329},{"type":"node","id":355920716,"lat":52.4791602,"lon":-1.8948123},{"type":"node","id":696842445,"lat":52.4795044,"lon":-1.8948359},{"type":"node","id":696848144,"lat":52.4792235,"lon":-1.8947898},{"type":"node","id":863896101,"lat":52.4784677,"lon":-1.8945658},{"type":"node","id":863896136,"lat":52.478718,"lon":-1.8951521},{"type":"node","id":863896139,"lat":52.4784671,"lon":-1.8945337},{"type":"node","id":864881342,"lat":52.4786653,"lon":-1.8948296},{"type":"node","id":908592240,"lat":52.4811968,"lon":-1.8963743},{"type":"node","id":908592241,"lat":52.4804042,"lon":-1.8952044},{"type":"node","id":955932442,"lat":52.4791925,"lon":-1.8948008},{"type":"node","id":955935291,"lat":52.4791177,"lon":-1.8948308},{"type":"node","id":956080706,"lat":52.4791487,"lon":-1.8949765},{"type":"node","id":956080710,"lat":52.4792745,"lon":-1.8949248},{"type":"node","id":1126389002,"lat":52.4787478,"lon":-1.8947979},{"type":"node","id":1126389003,"lat":52.4784774,"lon":-1.8942676},{"type":"node","id":1153441440,"lat":52.4797527,"lon":-1.8944326},{"type":"node","id":1261722715,"lat":52.4801087,"lon":-1.894681},{"type":"node","id":1261722728,"lat":52.4797719,"lon":-1.8947726},{"type":"node","id":1261722749,"lat":52.4796953,"lon":-1.8947841},{"type":"node","id":1455180568,"lat":52.4809556,"lon":-1.8959773},{"type":"node","id":1455180569,"lat":52.4829019,"lon":-1.8984106},{"type":"node","id":1455180570,"lat":52.4804203,"lon":-1.8951725},{"type":"node","id":1455180571,"lat":52.482865,"lon":-1.8984321},{"type":"node","id":1455180573,"lat":52.4828032,"lon":-1.8982901},{"type":"node","id":1744420726,"lat":52.4806541,"lon":-1.8956219},{"type":"node","id":1744420734,"lat":52.480931,"lon":-1.8959989},{"type":"node","id":1744420739,"lat":52.4813902,"lon":-1.8966493},{"type":"node","id":1827309427,"lat":52.482275,"lon":-1.897636},{"type":"node","id":1827309440,"lat":52.4806737,"lon":-1.895578},{"type":"node","id":1827309442,"lat":52.4815991,"lon":-1.8968425},{"type":"node","id":1975375864,"lat":52.478439,"lon":-1.8946622},{"type":"node","id":1975375865,"lat":52.4784497,"lon":-1.8945789},{"type":"node","id":1975383194,"lat":52.4785638,"lon":-1.8946978},{"type":"node","id":1975383212,"lat":52.4787206,"lon":-1.8946456},{"type":"node","id":4027013146,"lat":52.4801192,"lon":-1.8945596},{"type":"node","id":4027013149,"lat":52.4798006,"lon":-1.8945945},{"type":"node","id":4027013150,"lat":52.4797157,"lon":-1.8944175},{"type":"node","id":4027013156,"lat":52.4797826,"lon":-1.8945677},{"type":"node","id":4027013159,"lat":52.4797532,"lon":-1.894573},{"type":"node","id":4027013163,"lat":52.4801783,"lon":-1.8946775},{"type":"node","id":4027013168,"lat":52.4798251,"lon":-1.8946267},{"type":"node","id":4027013174,"lat":52.4797433,"lon":-1.8945513},{"type":"node","id":4027013184,"lat":52.4801486,"lon":-1.894514},{"type":"node","id":5505854516,"lat":52.4797937,"lon":-1.8944214},{"type":"node","id":6034972697,"lat":52.478502,"lon":-1.8946955},{"type":"node","id":6249629009,"lat":52.4786425,"lon":-1.8946715},{"type":"node","id":6410985128,"lat":52.4788605,"lon":-1.8947567},{"type":"node","id":6441628606,"lat":52.4793332,"lon":-1.8945913},{"type":"node","id":6441628607,"lat":52.479287,"lon":-1.8942776},{"type":"node","id":6441628608,"lat":52.4793702,"lon":-1.8947274},{"type":"node","id":6441628609,"lat":52.4793502,"lon":-1.8945847},{"type":"node","id":6441628610,"lat":52.4793055,"lon":-1.8942832},{"type":"node","id":7117546479,"lat":52.4812197,"lon":-1.8963484},{"type":"node","id":7117546480,"lat":52.4799551,"lon":-1.8943268},{"type":"node","id":10762333871,"lat":52.479565,"lon":-1.8947995},{"type":"node","id":10762333877,"lat":52.4786998,"lon":-1.8950127},{"type":"node","id":21392706,"lat":52.47914,"lon":-1.8925466},{"type":"node","id":90052951,"lat":52.4794255,"lon":-1.8930894},{"type":"node","id":90052953,"lat":52.4785948,"lon":-1.8937959},{"type":"node","id":90052954,"lat":52.4791832,"lon":-1.8934171},{"type":"node","id":178916275,"lat":52.4796662,"lon":-1.8938089},{"type":"node","id":273036406,"lat":52.4785568,"lon":-1.8938362},{"type":"node","id":310651596,"lat":52.4796519,"lon":-1.8939411},{"type":"node","id":313191017,"lat":52.4792353,"lon":-1.893496},{"type":"node","id":313191019,"lat":52.4786181,"lon":-1.8938562},{"type":"node","id":313191020,"lat":52.4785626,"lon":-1.8939454},{"type":"node","id":313191024,"lat":52.4795567,"lon":-1.8938847},{"type":"node","id":313191025,"lat":52.4794152,"lon":-1.8933521},{"type":"node","id":863896111,"lat":52.4793673,"lon":-1.8933395},{"type":"node","id":863896138,"lat":52.4793268,"lon":-1.8932371},{"type":"node","id":1455177634,"lat":52.4791677,"lon":-1.8925298},{"type":"node","id":1455180572,"lat":52.4796928,"lon":-1.8937909},{"type":"node","id":1580643689,"lat":52.4796799,"lon":-1.8936774},{"type":"node","id":1580643691,"lat":52.4800354,"lon":-1.8934762},{"type":"node","id":1580645684,"lat":52.4795898,"lon":-1.8933745},{"type":"node","id":1580645687,"lat":52.4799996,"lon":-1.893102},{"type":"node","id":1580645688,"lat":52.4800651,"lon":-1.8934426},{"type":"node","id":1683193631,"lat":52.4797585,"lon":-1.8932567},{"type":"node","id":2520425393,"lat":52.4790708,"lon":-1.8934894},{"type":"node","id":2523807528,"lat":52.4796514,"lon":-1.8937055},{"type":"node","id":5505854514,"lat":52.4795467,"lon":-1.8935162},{"type":"node","id":5505854515,"lat":52.4795642,"lon":-1.8933512},{"type":"node","id":6410985129,"lat":52.4788344,"lon":-1.8936959},{"type":"node","id":6410985130,"lat":52.4786956,"lon":-1.8937831},{"type":"node","id":6410985131,"lat":52.4788786,"lon":-1.8935423},{"type":"node","id":6410985132,"lat":52.4790018,"lon":-1.8936047},{"type":"node","id":6464915489,"lat":52.4788099,"lon":-1.8935765},{"type":"node","id":6464915490,"lat":52.4789847,"lon":-1.8934894},{"type":"node","id":7117546477,"lat":52.4794793,"lon":-1.8933136},{"type":"node","id":7117546478,"lat":52.4794518,"lon":-1.8933267},{"type":"node","id":9135599700,"lat":52.4795133,"lon":-1.8933984}]}