{"version":0.6,"generator":"Overpass API 0.7.62.5 1bd436f1","osm3s":{"timestamp_osm_base":"2025-03-12T11:41:14Z","copyright":"The data included in this document is from www.openstreetmap.org. The data is made available under ODbL."},"elements":[{"type":"node","id":8644394500,"lat":6.2458016,"lon":-75.570174,"tags":{"highway":"crossing"}},{"type":"node","id":12532788817,"lat":6.2459904,"lon":-75.5705183,"tags":{"addr:city":"Medell\u00edn","addr:full":"Calle 45 # 51 - 14 Taller de Joyeria Leidy Galvis","addr:postcode":"050012","contact:facebook":"61572450449362","contact:instagram":"leidygalvis_joyeria","image":"https:\/\/www.google.com\/local\/imagery\/report\/?cb_client=local_photo_viewer&image_key=!1e10!2sAF1QipPW52C7pmNT_XSWZ_2ztlElLxZvSLXaYOazFElM","name":"Taller de Joyeria Leidy Galvis","opening_hours":"Mo-Su 09:00-19:00","operator":"Taller de Joyeria Leidy Galvis.","payment:cash":"yes","payment:credit_cards":"yes","payment:debit_cards":"yes","payment:transferencia":"yes","phone":"+573216762014","shop":"jewelry","website":"https:\/\/www.leidygalvis.com"}}]}