{"place_id":164741895,"licence":"Data \u00a9 OpenStreetMap contributors, ODbL 1.0. http:\/\/osm.org\/copyright","osm_type":"way","osm_id":1133492257,"lat":"52.2264086","lon":"21.015115723112128","class":"amenity","type":"parking","place_rank":30,"importance":8.366292820625647e-5,"addresstype":"amenity","name":"","display_name":"Ho\u017ca, Marsza\u0142kowska Dzielnica Mieszkaniowa, \u015ar\u00f3dmie\u015bcie Po\u0142udniowe, Midtown, Warsaw, Masovian Voivodeship, 00-521, Poland","address":{"road":"Ho\u017ca","neighbourhood":"Marsza\u0142kowska Dzielnica Mieszkaniowa","quarter":"\u015ar\u00f3dmie\u015bcie Po\u0142udniowe","suburb":"Midtown","city":"Warsaw","state":"Masovian Voivodeship","ISO3166-2-lvl4":"PL-14","postcode":"00-521","country":"Poland","country_code":"pl"},"boundingbox":["52.2262911","52.2265261","21.0145998","21.0156316"]}