{"place_id":164619717,"licence":"Data \u00a9 OpenStreetMap contributors, ODbL 1.0. http:\/\/osm.org\/copyright","osm_type":"way","osm_id":1189746104,"lat":"52.2284821","lon":"21.016411804457007","class":"amenity","type":"parking","place_rank":30,"importance":8.366292820625647e-5,"addresstype":"amenity","name":"","display_name":"\u017burawia, \u015ar\u00f3dmie\u015bcie Po\u0142udniowe, Midtown, Warsaw, Masovian Voivodeship, 00-512, Poland","address":{"road":"\u017burawia","quarter":"\u015ar\u00f3dmie\u015bcie Po\u0142udniowe","suburb":"Midtown","city":"Warsaw","state":"Masovian Voivodeship","ISO3166-2-lvl4":"PL-14","postcode":"00-512","country":"Poland","country_code":"pl"},"boundingbox":["52.2282532","52.2286882","21.0154816","21.0171582"]}