{"place_id":258601670,"licence":"Data \u00a9 OpenStreetMap contributors, ODbL 1.0. http:\/\/osm.org\/copyright","osm_type":"way","osm_id":398496680,"lat":"52.4792907","lon":"-1.9018372057255677","class":"amenity","type":"fast_food","place_rank":30,"importance":7.734416723883447e-5,"addresstype":"amenity","name":"Greggs","display_name":"Greggs, 85, New Street, Chinese Quarter, Edgbaston, Park Central, Birmingham, West Midlands, England, B2 4BA, United Kingdom","address":{"amenity":"Greggs","house_number":"85","road":"New Street","neighbourhood":"Chinese Quarter","suburb":"Edgbaston","village":"Park Central","city":"Birmingham","ISO3166-2-lvl8":"GB-BIR","state_district":"West Midlands","state":"England","ISO3166-2-lvl4":"GB-ENG","postcode":"B2 4BA","country":"United Kingdom","country_code":"gb"},"boundingbox":["52.4792365","52.4793449","-1.9018928","-1.9017811"]}