{"place_id":285739901,"licence":"Data \u00a9 OpenStreetMap contributors, ODbL 1.0. http:\/\/osm.org\/copyright","osm_type":"node","osm_id":7239647785,"lat":"6.2467398","lon":"-75.5687819","class":"amenity","type":"restaurant","place_rank":30,"importance":6.934843976496555e-5,"addresstype":"amenity","name":"Hotdog","display_name":"Hotdog, Calle 47, Col\u00f3n, Comuna 10 - La Candelaria, Medell\u00edn, Valle de Aburr\u00e1, Antioquia, RAP del Agua y la Monta\u00f1a, 050015, Colombia","address":{"amenity":"Hotdog","road":"Calle 47","neighbourhood":"Col\u00f3n","suburb":"Comuna 10 - La Candelaria","city":"Medell\u00edn","state_district":"Valle de Aburr\u00e1","state":"Antioquia","ISO3166-2-lvl4":"CO-ANT","region":"RAP del Agua y la Monta\u00f1a","postcode":"050015","country":"Colombia","country_code":"co"},"boundingbox":["6.2466898","6.2467898","-75.5688319","-75.5687319"]}