{"place_id":286646887,"licence":"Data \u00a9 OpenStreetMap contributors, ODbL 1.0. http:\/\/osm.org\/copyright","osm_type":"way","osm_id":31973366,"lat":"6.249006250000001","lon":"-75.57044094173482","class":"historic","type":"monument","place_rank":30,"importance":6.934843976496555e-5,"addresstype":"historic","name":"Palacio Nacional","display_name":"Palacio Nacional, Carrera 52, Guayaquil, Comuna 10 - La Candelaria, Medell\u00edn, Valle de Aburr\u00e1, Antioquia, RAP del Agua y la Monta\u00f1a, 050015, Colombia","address":{"historic":"Palacio Nacional","road":"Carrera 52","neighbourhood":"Guayaquil","suburb":"Comuna 10 - La Candelaria","city":"Medell\u00edn","state_district":"Valle de Aburr\u00e1","state":"Antioquia","ISO3166-2-lvl4":"CO-ANT","region":"RAP del Agua y la Monta\u00f1a","postcode":"050015","country":"Colombia","country_code":"co"},"boundingbox":["6.2486032","6.2494158","-75.5706815","-75.5701217"]}