{"place_id":154837717,"licence":"Data \u00a9 OpenStreetMap contributors, ODbL 1.0. http:\/\/osm.org\/copyright","osm_type":"way","osm_id":1267897850,"lat":"60.187755","lon":"24.95904997367702","class":"leisure","type":"playground","place_rank":30,"importance":8.385061417558583e-5,"addresstype":"leisure","name":"","display_name":"Helsinginkatu, Kurvi, Harju, Alppiharju, Central major district, Helsinki, Helsinki sub-region, Uusimaa, Mainland Finland, 00500, Finland","address":{"road":"Helsinginkatu","neighbourhood":"Kurvi","quarter":"Harju","suburb":"Alppiharju","city_district":"Central major district","city":"Helsinki","municipality":"Helsinki sub-region","state":"Uusimaa","ISO3166-2-lvl4":"FI-18","region":"Mainland Finland","postcode":"00500","country":"Finland","country_code":"fi"},"boundingbox":["60.1876303","60.1879315","24.9587390","24.9593637"]}